pypi_hw/__init__.py
pypi_hw/_static_version.py
pypi_hw/_version.py
pypi_hw-0.0.1.dist-info/LICENSE
pypi_hw-0.0.1.dist-info/METADATA
pypi_hw-0.0.1.dist-info/WHEEL
pypi_hw-0.0.1.dist-info/top_level.txt
pypi_hw-0.0.1.dist-info/RECORD
